LICENSE
README.md
setup.py
api/main.py
api/models.py
api/handlers/__init__.py
api/handlers/prompt.py
pozdnyakov/__init__.py
pozdnyakov.egg-info/PKG-INFO
pozdnyakov.egg-info/SOURCES.txt
pozdnyakov.egg-info/dependency_links.txt
pozdnyakov.egg-info/requires.txt
pozdnyakov.egg-info/top_level.txt
pozdnyakov/chatbot/__init__.py
pozdnyakov/chatbot/config.py
pozdnyakov/chatbot/utils.py
telegram/config.py
telegram/main.py
telegram/handlers/__init__.py
telegram/handlers/prompt.py