Metadata-Version: 2.1
Name: pozdnyakov
Version: 1488
Summary: Library to talk with Pozdnyakov (наш слоняра)
Home-page: https://github.com/sodeeplearning/Pozdnyakov-Vlad-AI
Author: Vitally Petreev
Author-email: vitaliy.petreev@gmail.com
License: MIT License, see LICENSE file
Requires-Python: >=3.9
License-File: LICENSE
Requires-Dist: transformers
Requires-Dist: accelerate
Requires-Dist: bitsandbytes
Requires-Dist: torch
